{
  "swagger": "2.0",
  "info": {
    "title": "API Fatec",
    "description": "Documentação da API usando Swagger",
    "version": "1.0.0"
  },
  "host": "localhost:3000",
  "basePath": "/",
  "schemes": [
    "http"
  ],
  "securityDefinitions": {
    "apiKeyAuth": {
      "type": "apiKey",
      "in": "header",
      "name": "x-api-key"
    }
  },
  "paths": {
    "/user": {
      "get": {
        "description": "",
        "responses": {
          "200": {
            "description": "OK"
          },
          "403": {
            "description": "Forbidden"
          },
          "500": {
            "description": "Internal Server Error"
          }
        }
      },
      "post": {
        "description": "",
        "parameters": [
          {
            "name": "body",
            "in": "body",
            "schema": {
              "type": "object",
              "properties": {
                "name": {
                  "example": "any"
                },
                "age": {
                  "example": "any"
                }
              }
            }
          }
        ],
        "responses": {
          "201": {
            "description": "Created"
          },
          "403": {
            "description": "Forbidden"
          },
          "500": {
            "description": "Internal Server Error"
          }
        }
      }
    },
    "/user/{id}": {
      "get": {
        "description": "",
        "parameters": [
          {
            "name": "id",
            "in": "path",
            "required": true,
            "type": "string"
          }
        ],
        "responses": {
          "200": {
            "description": "OK"
          },
          "403": {
            "description": "Forbidden"
          },
          "500": {
            "description": "Internal Server Error"
          }
        }
      },
      "delete": {
        "description": "",
        "parameters": [
          {
            "name": "id",
            "in": "path",
            "required": true,
            "type": "string"
          }
        ],
        "responses": {
          "200": {
            "description": "OK"
          },
          "403": {
            "description": "Forbidden"
          },
          "500": {
            "description": "Internal Server Error"
          }
        }
      },
      "put": {
        "description": "",
        "parameters": [
          {
            "name": "id",
            "in": "path",
            "required": true,
            "type": "string"
          },
          {
            "name": "body",
            "in": "body",
            "schema": {
              "type": "object",
              "properties": {
                "name": {
                  "example": "any"
                },
                "age": {
                  "example": "any"
                }
              }
            }
          }
        ],
        "responses": {
          "200": {
            "description": "OK"
          },
          "403": {
            "description": "Forbidden"
          },
          "500": {
            "description": "Internal Server Error"
          }
        }
      }
    },
    "/project": {
      "get": {
        "description": "",
        "responses": {
          "200": {
            "description": "OK"
          },
          "403": {
            "description": "Forbidden"
          },
          "500": {
            "description": "Internal Server Error"
          }
        }
      },
      "post": {
        "description": "",
        "parameters": [
          {
            "name": "body",
            "in": "body",
            "schema": {
              "type": "object",
              "properties": {
                "title": {
                  "example": "any"
                },
                "description": {
                  "example": "any"
                },
                "assignedTo": {
                  "example": "any"
                }
              }
            }
          }
        ],
        "responses": {
          "201": {
            "description": "Created"
          },
          "403": {
            "description": "Forbidden"
          },
          "500": {
            "description": "Internal Server Error"
          }
        }
      }
    },
    "/project/{id}": {
      "get": {
        "description": "",
        "parameters": [
          {
            "name": "id",
            "in": "path",
            "required": true,
            "type": "string"
          }
        ],
        "responses": {
          "200": {
            "description": "OK"
          },
          "403": {
            "description": "Forbidden"
          },
          "500": {
            "description": "Internal Server Error"
          }
        }
      }
    }
  },
  "security": [
    {
      "apiKeyAuth": []
    }
  ]
}